reacTk/__init__.py
reacTk/util.py
reacTk/decorator/__init__.py
reacTk/decorator/asynchron.py
reacTk/decorator/recurrency_filter.py
reacTk/decorator/stateful.py
reacTk/state/__init__.py
reacTk/state/bounding_box.py
reacTk/state/contour.py
reacTk/state/point.py
reacTk/state/util.py
reacTk/widget/__init__.py
reacTk/widget/chechbox.py
reacTk/widget/label.py
reacTk/widget/canvas/__init__.py
reacTk/widget/canvas/bounding_box.py
reacTk/widget/canvas/canvas.py
reacTk/widget/canvas/circle.py
reacTk/widget/canvas/contour.py
reacTk/widget/canvas/image.py
reacTk/widget/canvas/lib.py
reacTk/widget/canvas/line.py
reacTk/widget/canvas/rectangle.py
reacTk/widget/canvas/text.py
reactk-0.0.7.dist-info/METADATA
reactk-0.0.7.dist-info/WHEEL
reactk-0.0.7.dist-info/licenses/LICENSE
reactk-0.0.7.dist-info/RECORD
