Metadata-Version: 2.4
Name: reacTk
Version: 0.0.7
Summary: Tk widgets using the widget_state library.
Project-URL: Homepage, https://github.com/pLeminoq/reacTk
Author-email: Tamino Huxohl <thuxohl@mailbox.org>
License-File: LICENSE
Classifier: License :: OSI Approved :: MIT License
Classifier: Operating System :: OS Independent
Classifier: Programming Language :: Python :: 3
Requires-Python: >=3.10
Requires-Dist: numpy>=1.26.0
Requires-Dist: opencv-python>=4.10.0.84
Requires-Dist: pillow>=11.0.0
Requires-Dist: screeninfo>=0.8.1
Requires-Dist: widget-state>=0.0.7
